.gitmodules
LICENSE
MANIFEST.in
pyproject.toml
release.sh
setup.py
examples/hllhc14_collision/000_build_collider_from_mad_model.py
examples/hllhc14_collision/001_install_beambeam.py
examples/hllhc14_collision/002_knobs_and_tuning.py
examples/hllhc14_collision/003_lumi_level.py
examples/hllhc14_collision/004_configure_beambeam.py
examples/hllhc14_collision/config.yaml
examples/hllhc14_collision/gen_config_orbit_correction.py
examples/hllhc14_collision/optics_specific_tools_hlhc14.py
examples/hllhc15_collision/000_build_collider_from_mad_model.py
examples/hllhc15_collision/001_install_beambeam.py
examples/hllhc15_collision/002_knobs_and_tuning.py
examples/hllhc15_collision/003_lumi_level.py
examples/hllhc15_collision/004_configure_beambeam.py
examples/hllhc15_collision/005_footprint.py
examples/hllhc15_collision/config.yaml
examples/hllhc15_collision/gen_config_orbit_correction.py
examples/hllhc15_collision/optics_specific_tools_hlhc15.py
examples/multiline_matching/000_multiline_match.py
examples/multiline_matching/001_match_lumi_with_target.py
examples/run3_collision_no_bb_with_apertures/000_build_collider_from_mad_model.py
examples/run3_collision_no_bb_with_apertures/002_knobs_and_tuning.py
examples/run3_collision_no_bb_with_apertures/config.yaml
examples/run3_collision_no_bb_with_apertures/optics_specific_tools_run3.py
examples/run3_collision_no_bb_with_apertures/t000_test_mad_model.py
examples/run3_collision_no_bb_with_apertures/track_levelling.20_b1.madx
examples/run3_ions/000_build_collider_from_mad_model.py
examples/run3_ions/001_install_beambeam.py
examples/run3_ions/002_knobs_and_tuning.py
examples/run3_ions/003_lumi_level.py
examples/run3_ions/004_configure_beambeam.py
examples/run3_ions/005_footprint.py
examples/run3_ions/config.yaml
examples/run3_ions/gen_config_orbit_correction.py
examples/run3_ions/optics_specific_tools_ions_run3.py
test_data/hllhc14/README.md
test_data/hllhc14/hllhc_sequence.madx
test_data/hllhc14/job_tracking.mask
xmask.egg-info/PKG-INFO
xmask.egg-info/SOURCES.txt
xmask.egg-info/dependency_links.txt
xmask.egg-info/requires.txt
xmask.egg-info/top_level.txt
