Metadata-Version: 2.1
Name: xmask
Version: 0.4.1
Summary: Configuration of tracking simulations for the LHC and other accelerators
Home-page: https://github.com/xsuite/xsuite/issues
Download-URL: https://pypi.python.org/pypi/xmask
Author: G. Iadarola et al.
License: Apache 2.0
Project-URL: Bug Tracker, https://github.com/xsuite/xsuite/issues
Project-URL: Source Code, https://github.com/xsuite/xmask/
License-File: LICENSE
Requires-Dist: numpy>=1.0
Requires-Dist: pyyaml
Requires-Dist: xfields
Provides-Extra: tests
Requires-Dist: cpymad; extra == "tests"
Requires-Dist: pytest; extra == "tests"
